setup.cfg
setup.py
Migration.egg-info/PKG-INFO
Migration.egg-info/SOURCES.txt
Migration.egg-info/dependency_links.txt
Migration.egg-info/entry_points.txt
Migration.egg-info/not-zip-safe
Migration.egg-info/requires.txt
Migration.egg-info/top_level.txt
migration/__init__.py
migration/base_classes.py
migration/migrate_command.py
migration/migration.py
migration/package.py
migration/schema_generator.py
migration/sqlalchemy_migration.py
migration/sqlobject_migration.py
migration/tickets.txt
