Metadata-Version: 1.0
Name: Migration
Version: 0.2a4.dev-r413
Summary: A database/model migration extension for TurboGears
Home-page: UNKNOWN
Author: Claudio Martinez
Author-email: claudio.s.martinez@gmail.com
License: UNKNOWN
Platform: UNKNOWN
Classifier: Development Status :: 3 - Alpha
Classifier: Operating System :: OS Independent
Classifier: Programming Language :: Python
Classifier: Topic :: Software Development :: Libraries :: Python Modules
Classifier: Framework :: TurboGears
